Metadata-Version: 2.4
Name: aiogram-mgr
Version: 1.0.0
Summary: A command-line tool used to create aiogram projects and maybe more things soon.
Requires-Python: >=3.9
Requires-Dist: aiogram
Requires-Dist: pydantic
Requires-Dist: pydantic-settings
Requires-Dist: watchdog
Requires-Dist: cookiecutter
Requires-Dist: click
Requires-Dist: rich
